spritePro/__init__.py
spritePro/button.py
spritePro/constants.py
spritePro/particles.py
spritePro/sprite.py
spritePro/spriteProGame.py
spritePro/toggle_button.py
spritePro/audio/__init__.py
spritePro/audio/audio_manager.py
spritePro/components/__init__.py
spritePro/components/animation.py
spritePro/components/health.py
spritePro/components/mouse_interactor.py
spritePro/components/text.py
spritePro/components/timer.py
spritePro/components/tween.py
spritePro/demoGames/amongus.py
spritePro/demoGames/animationDemo.py
spritePro/demoGames/bar_demo.py
spritePro/demoGames/bar_hp_demo.py
spritePro/demoGames/bar_simple_demo.py
spritePro/demoGames/child_movement_demo.py
spritePro/demoGames/color_text_demo.py
spritePro/demoGames/demo_pymunk.py
spritePro/demoGames/easy_clicker.py
spritePro/demoGames/fireworks_demo.py
spritePro/demoGames/hero_vs_enemy.py
spritePro/demoGames/particle_demo.py
spritePro/demoGames/particle_template_test.py
spritePro/demoGames/particles_images_demo.py
spritePro/demoGames/particles_templates_demo.py
spritePro/demoGames/ping_pong.py
spritePro/demoGames/save_load_demo.py
spritePro/demoGames/sorting_order_demo.py
spritePro/demoGames/test_horror.py
spritePro/demoGames/text_fps_demo.py
spritePro/demoGames/toggle_demo.py
spritePro/demoGames/tweenDemo.py
spritePro/demoGames/fps_camera_demo/fps_camera_demo.py
spritePro/demoGames/ping_pong/event_bus.py
spritePro/demoGames/ping_pong/game.py
spritePro/demoGames/ping_pong/main.py
spritePro/demoGames/ping_pong/game_objects/ball.py
spritePro/demoGames/ping_pong/game_objects/platform.py
spritePro/readySprites/__init__.py
spritePro/readySprites/bar.py
spritePro/readySprites/text_fps.py
spritePro/utils/__init__.py
spritePro/utils/color_effects.py
spritePro/utils/save_load.py
spritePro/utils/surface.py
spritepro-1.0.2.dist-info/METADATA
spritepro-1.0.2.dist-info/WHEEL
spritepro-1.0.2.dist-info/top_level.txt
spritepro-1.0.2.dist-info/RECORD
