Metadata-Version: 2.4
Name: spritepro
Version: 1.0.2
Summary: A high-level 2D game framework for Python, built on Pygame, designed to simplify and speed up game development.
Author-email: NeoXider <author@example.com>
Project-URL: Homepage, https://github.com/NeoXider/SpritePro
Project-URL: Issues, https://github.com/NeoXider/SpritePro/issues
Classifier: Development Status :: 4 - Beta
Classifier: Intended Audience :: Developers
Classifier: License :: OSI Approved :: MIT License
Classifier: Operating System :: OS Independent
Classifier: Programming Language :: Python :: 3
Classifier: Programming Language :: Python :: 3.7
Classifier: Programming Language :: Python :: 3.8
Classifier: Programming Language :: Python :: 3.9
Classifier: Programming Language :: Python :: 3.10
Classifier: Programming Language :: Python :: 3.11
Classifier: Topic :: Games/Entertainment
Classifier: Topic :: Software Development :: Libraries :: Application Frameworks
Requires-Python: >=3.7
Requires-Dist: pygame>=2.0.0
